bluesky_gym/README.md
bluesky_gym/__init__.py
bluesky_gym/envs/README.md
bluesky_gym/envs/__init__.py
bluesky_gym/envs/descent_env.py
bluesky_gym/envs/horizontal_cr_env.py
bluesky_gym/envs/merge_env.py
bluesky_gym/envs/plan_waypoint_env.py
bluesky_gym/envs/sector_cr_env.py
bluesky_gym/envs/static_obstacle_env.py
bluesky_gym/envs/vertical_cr_env.py
bluesky_gym/envs/common/functions.py
bluesky_gym/envs/common/polygon_generator.py
bluesky_gym/envs/common/screen_dummy.py
bluesky_gym/utils/__init__.py
bluesky_gym/utils/logger.py
bluesky_gym-0.1.0.dist-info/METADATA
bluesky_gym-0.1.0.dist-info/WHEEL
bluesky_gym-0.1.0.dist-info/licenses/LICENSE
bluesky_gym-0.1.0.dist-info/RECORD
