Metadata-Version: 2.3
Name: bluesky-gym
Version: 0.1.0
Summary: A gymnasium style environment for standardized Reinforcement Learning research in Air Traffic Management.
Project-URL: Homepage, https://github.com/TUDelft-CNS-ATM/bluesky-gym
Project-URL: Issues, https://github.com/TUDelft-CNS-ATM/bluesky-gym/issues
Author-email: Jan Groot <d.j.groot@tudelft.nl>, Joost Ellerbroek <j.ellerbroek@tudelft.nl>, Giulia Leto <g.leto@tudelft.nl>, Sasha Vlaskin <a.vlaskin@tudelft.nl>
License-File: LICENSE
Classifier: Development Status :: 4 - Beta
Classifier: Intended Audience :: Science/Research
Classifier: License :: OSI Approved :: GNU General Public License v3 (GPLv3)
Classifier: Operating System :: OS Independent
Classifier: Programming Language :: Python :: 3
Classifier: Topic :: Scientific/Engineering
Requires-Python: >=3.10
Requires-Dist: bluesky-simulator
Requires-Dist: gymnasium
Requires-Dist: numpy==1.24
Requires-Dist: pygame==2.5.2
Requires-Dist: stable-baselines3==2.2.1
Requires-Dist: torch==2.2.0
